cgi_processor/__init__.py
cgi_processor/processor.py
cgi_processor-0.1.4.dist-info/LICENSE
cgi_processor-0.1.4.dist-info/METADATA
cgi_processor-0.1.4.dist-info/WHEEL
cgi_processor-0.1.4.dist-info/top_level.txt
cgi_processor-0.1.4.dist-info/RECORD
