Metadata-Version: 2.1
Name: cgi-processor
Version: 0.1.4
Summary: Модуль для предобработки текстов журнала «Цифровые гуманитарные исследования»
Home-page: https://github.com/nevmenandr/cgi_processor
Author: Boris Orekhov
Author-email: nevmenandr@gmail.com
License: UNKNOWN
Platform: UNKNOWN
Classifier: Programming Language :: Python :: 3
Classifier: License :: OSI Approved :: GNU General Public License v3 or later (GPLv3+)
Classifier: Operating System :: OS Independent
Requires-Python: >=3.7
License-File: LICENSE
